<?xml version='1.0' encoding='utf-8'?>
<Gesture Name="check" NumPts="331">
  <Point X="236" Y="327" T="1781630520857" />
  <Point X="237" Y="327" T="1781630520860" />
  <Point X="237" Y="327" T="1781630520866" />
  <Point X="238" Y="327" T="1781630520866" />
  <Point X="238" Y="327" T="1781630520869" />
  <Point X="243" Y="331" T="1781630520897" />
  <Point X="247" Y="336" T="1781630520912" />
  <Point X="248" Y="337" T="1781630520916" />
  <Point X="248" Y="337" T="1781630520916" />
  <Point X="248" Y="338" T="1781630520917" />
  <Point X="249" Y="338" T="1781630520918" />
  <Point X="249" Y="339" T="1781630520919" />
  <Point X="249" Y="340" T="1781630520920" />
  <Point X="250" Y="340" T="1781630520921" />
  <Point X="250" Y="340" T="1781630520922" />
  <Point X="250" Y="341" T="1781630520923" />
  <Point X="250" Y="341" T="1781630520924" />
  <Point X="251" Y="342" T="1781630520925" />
  <Point X="251" Y="342" T="1781630520926" />
  <Point X="252" Y="343" T="1781630520927" />
  <Point X="252" Y="344" T="1781630520928" />
  <Point X="254" Y="347" T="1781630520932" />
  <Point X="254" Y="347" T="1781630520933" />
  <Point X="254" Y="348" T="1781630520934" />
  <Point X="255" Y="349" T="1781630520935" />
  <Point X="255" Y="349" T="1781630520936" />
  <Point X="256" Y="351" T="1781630520938" />
  <Point X="256" Y="351" T="1781630520939" />
  <Point X="256" Y="352" T="1781630520940" />
  <Point X="257" Y="353" T="1781630520941" />
  <Point X="257" Y="353" T="1781630520942" />
  <Point X="257" Y="353" T="1781630520943" />
  <Point X="258" Y="354" T="1781630520944" />
  <Point X="260" Y="358" T="1781630520947" />
  <Point X="260" Y="359" T="1781630520947" />
  <Point X="261" Y="360" T="1781630520948" />
  <Point X="261" Y="361" T="1781630520949" />
  <Point X="262" Y="361" T="1781630520950" />
  <Point X="262" Y="362" T="1781630520951" />
  <Point X="262" Y="363" T="1781630520952" />
  <Point X="262" Y="363" T="1781630520953" />
  <Point X="263" Y="364" T="1781630520954" />
  <Point X="263" Y="364" T="1781630520955" />
  <Point X="264" Y="365" T="1781630520956" />
  <Point X="264" Y="366" T="1781630520957" />
  <Point X="264" Y="366" T="1781630520958" />
  <Point X="265" Y="367" T="1781630520959" />
  <Point X="265" Y="368" T="1781630520960" />
  <Point X="266" Y="368" T="1781630520961" />
  <Point X="267" Y="371" T="1781630520965" />
  <Point X="267" Y="372" T="1781630520966" />
  <Point X="268" Y="373" T="1781630520967" />
  <Point X="268" Y="373" T="1781630520968" />
  <Point X="269" Y="374" T="1781630520969" />
  <Point X="269" Y="374" T="1781630520970" />
  <Point X="269" Y="375" T="1781630520971" />
  <Point X="270" Y="376" T="1781630520972" />
  <Point X="270" Y="377" T="1781630520973" />
  <Point X="271" Y="377" T="1781630520974" />
  <Point X="271" Y="378" T="1781630520975" />
  <Point X="271" Y="378" T="1781630520976" />
  <Point X="271" Y="379" T="1781630520977" />
  <Point X="272" Y="380" T="1781630520978" />
  <Point X="272" Y="380" T="1781630520980" />
  <Point X="273" Y="381" T="1781630520980" />
  <Point X="273" Y="382" T="1781630520982" />
  <Point X="273" Y="382" T="1781630520983" />
  <Point X="274" Y="383" T="1781630520984" />
  <Point X="274" Y="384" T="1781630520985" />
  <Point X="274" Y="384" T="1781630520986" />
  <Point X="275" Y="384" T="1781630520988" />
  <Point X="275" Y="385" T="1781630520988" />
  <Point X="275" Y="386" T="1781630520989" />
  <Point X="276" Y="387" T="1781630520990" />
  <Point X="276" Y="387" T="1781630520991" />
  <Point X="276" Y="387" T="1781630520992" />
  <Point X="277" Y="388" T="1781630520993" />
  <Point X="277" Y="389" T="1781630520994" />
  <Point X="278" Y="390" T="1781630520996" />
  <Point X="278" Y="390" T="1781630520997" />
  <Point X="278" Y="391" T="1781630520999" />
  <Point X="278" Y="391" T="1781630520999" />
  <Point X="279" Y="392" T="1781630521000" />
  <Point X="279" Y="392" T="1781630521001" />
  <Point X="279" Y="393" T="1781630521002" />
  <Point X="280" Y="393" T="1781630521003" />
  <Point X="280" Y="394" T="1781630521004" />
  <Point X="280" Y="394" T="1781630521005" />
  <Point X="280" Y="395" T="1781630521006" />
  <Point X="281" Y="395" T="1781630521007" />
  <Point X="281" Y="396" T="1781630521008" />
  <Point X="281" Y="396" T="1781630521009" />
  <Point X="282" Y="397" T="1781630521010" />
  <Point X="282" Y="397" T="1781630521011" />
  <Point X="282" Y="397" T="1781630521013" />
  <Point X="282" Y="398" T="1781630521013" />
  <Point X="282" Y="399" T="1781630521014" />
  <Point X="283" Y="399" T="1781630521016" />
  <Point X="283" Y="400" T="1781630521016" />
  <Point X="283" Y="400" T="1781630521017" />
  <Point X="284" Y="400" T="1781630521018" />
  <Point X="284" Y="401" T="1781630521020" />
  <Point X="284" Y="401" T="1781630521020" />
  <Point X="285" Y="402" T="1781630521021" />
  <Point X="285" Y="402" T="1781630521022" />
  <Point X="285" Y="402" T="1781630521023" />
  <Point X="285" Y="403" T="1781630521024" />
  <Point X="286" Y="403" T="1781630521025" />
  <Point X="286" Y="404" T="1781630521026" />
  <Point X="286" Y="404" T="1781630521027" />
  <Point X="286" Y="404" T="1781630521028" />
  <Point X="287" Y="405" T="1781630521030" />
  <Point X="287" Y="406" T="1781630521031" />
  <Point X="287" Y="406" T="1781630521033" />
  <Point X="288" Y="406" T="1781630521034" />
  <Point X="288" Y="407" T="1781630521035" />
  <Point X="288" Y="407" T="1781630521036" />
  <Point X="289" Y="408" T="1781630521038" />
  <Point X="289" Y="408" T="1781630521039" />
  <Point X="289" Y="408" T="1781630521041" />
  <Point X="290" Y="409" T="1781630521043" />
  <Point X="290" Y="409" T="1781630521044" />
  <Point X="290" Y="410" T="1781630521046" />
  <Point X="291" Y="410" T="1781630521047" />
  <Point X="291" Y="410" T="1781630521048" />
  <Point X="291" Y="410" T="1781630521050" />
  <Point X="291" Y="410" T="1781630521050" />
  <Point X="291" Y="410" T="1781630521051" />
  <Point X="291" Y="411" T="1781630521053" />
  <Point X="292" Y="411" T="1781630521054" />
  <Point X="292" Y="411" T="1781630521056" />
  <Point X="293" Y="411" T="1781630521058" />
  <Point X="293" Y="412" T="1781630521059" />
  <Point X="293" Y="412" T="1781630521060" />
  <Point X="293" Y="412" T="1781630521063" />
  <Point X="294" Y="412" T="1781630521064" />
  <Point X="294" Y="412" T="1781630521067" />
  <Point X="294" Y="413" T="1781630521071" />
  <Point X="295" Y="413" T="1781630521074" />
  <Point X="295" Y="413" T="1781630521081" />
  <Point X="296" Y="413" T="1781630521084" />
  <Point X="296" Y="413" T="1781630521091" />
  <Point X="296" Y="413" T="1781630521091" />
  <Point X="297" Y="413" T="1781630521097" />
  <Point X="297" Y="413" T="1781630521098" />
  <Point X="298" Y="413" T="1781630521101" />
  <Point X="298" Y="412" T="1781630521102" />
  <Point X="298" Y="412" T="1781630521103" />
  <Point X="298" Y="412" T="1781630521105" />
  <Point X="299" Y="412" T="1781630521107" />
  <Point X="299" Y="411" T="1781630521108" />
  <Point X="299" Y="411" T="1781630521110" />
  <Point X="300" Y="411" T="1781630521111" />
  <Point X="300" Y="410" T="1781630521114" />
  <Point X="301" Y="410" T="1781630521114" />
  <Point X="301" Y="410" T="1781630521115" />
  <Point X="301" Y="409" T="1781630521118" />
  <Point X="302" Y="409" T="1781630521118" />
  <Point X="302" Y="408" T="1781630521119" />
  <Point X="302" Y="408" T="1781630521120" />
  <Point X="303" Y="408" T="1781630521121" />
  <Point X="303" Y="407" T="1781630521122" />
  <Point X="303" Y="407" T="1781630521123" />
  <Point X="304" Y="406" T="1781630521124" />
  <Point X="304" Y="406" T="1781630521125" />
  <Point X="305" Y="405" T="1781630521126" />
  <Point X="305" Y="405" T="1781630521127" />
  <Point X="306" Y="404" T="1781630521128" />
  <Point X="307" Y="403" T="1781630521130" />
  <Point X="307" Y="403" T="1781630521131" />
  <Point X="308" Y="402" T="1781630521132" />
  <Point X="309" Y="401" T="1781630521134" />
  <Point X="309" Y="400" T="1781630521135" />
  <Point X="310" Y="399" T="1781630521136" />
  <Point X="311" Y="398" T="1781630521138" />
  <Point X="312" Y="397" T="1781630521139" />
  <Point X="312" Y="397" T="1781630521140" />
  <Point X="313" Y="396" T="1781630521141" />
  <Point X="314" Y="396" T="1781630521142" />
  <Point X="314" Y="395" T="1781630521143" />
  <Point X="315" Y="394" T="1781630521144" />
  <Point X="316" Y="393" T="1781630521147" />
  <Point X="317" Y="392" T="1781630521147" />
  <Point X="318" Y="390" T="1781630521148" />
  <Point X="320" Y="389" T="1781630521149" />
  <Point X="321" Y="387" T="1781630521152" />
  <Point X="322" Y="387" T="1781630521152" />
  <Point X="323" Y="386" T="1781630521153" />
  <Point X="323" Y="385" T="1781630521154" />
  <Point X="325" Y="384" T="1781630521155" />
  <Point X="326" Y="383" T="1781630521156" />
  <Point X="326" Y="383" T="1781630521157" />
  <Point X="327" Y="382" T="1781630521158" />
  <Point X="332" Y="377" T="1781630521159" />
  <Point X="332" Y="376" T="1781630521160" />
  <Point X="333" Y="375" T="1781630521161" />
  <Point X="334" Y="374" T="1781630521164" />
  <Point X="339" Y="370" T="1781630521164" />
  <Point X="342" Y="367" T="1781630521165" />
  <Point X="343" Y="366" T="1781630521166" />
  <Point X="343" Y="366" T="1781630521168" />
  <Point X="345" Y="364" T="1781630521168" />
  <Point X="350" Y="360" T="1781630521169" />
  <Point X="351" Y="358" T="1781630521170" />
  <Point X="353" Y="357" T="1781630521171" />
  <Point X="355" Y="354" T="1781630521172" />
  <Point X="360" Y="350" T="1781630521173" />
  <Point X="363" Y="348" T="1781630521174" />
  <Point X="364" Y="347" T="1781630521175" />
  <Point X="367" Y="344" T="1781630521176" />
  <Point X="368" Y="343" T="1781630521177" />
  <Point X="369" Y="342" T="1781630521178" />
  <Point X="380" Y="332" T="1781630521181" />
  <Point X="383" Y="330" T="1781630521181" />
  <Point X="383" Y="330" T="1781630521182" />
  <Point X="395" Y="320" T="1781630521185" />
  <Point X="397" Y="317" T="1781630521185" />
  <Point X="401" Y="315" T="1781630521186" />
  <Point X="406" Y="311" T="1781630521188" />
  <Point X="411" Y="307" T="1781630521189" />
  <Point X="411" Y="307" T="1781630521190" />
  <Point X="417" Y="303" T="1781630521191" />
  <Point X="420" Y="300" T="1781630521192" />
  <Point X="421" Y="299" T="1781630521193" />
  <Point X="423" Y="298" T="1781630521194" />
  <Point X="432" Y="291" T="1781630521197" />
  <Point X="432" Y="291" T="1781630521197" />
  <Point X="438" Y="287" T="1781630521198" />
  <Point X="440" Y="286" T="1781630521199" />
  <Point X="446" Y="281" T="1781630521202" />
  <Point X="451" Y="278" T="1781630521202" />
  <Point X="452" Y="277" T="1781630521203" />
  <Point X="458" Y="274" T="1781630521204" />
  <Point X="466" Y="268" T="1781630521205" />
  <Point X="468" Y="267" T="1781630521206" />
  <Point X="468" Y="267" T="1781630521207" />
  <Point X="477" Y="261" T="1781630521208" />
  <Point X="480" Y="259" T="1781630521209" />
  <Point X="481" Y="259" T="1781630521210" />
  <Point X="489" Y="255" T="1781630521211" />
  <Point X="492" Y="252" T="1781630521213" />
  <Point X="501" Y="246" T="1781630521214" />
  <Point X="503" Y="245" T="1781630521215" />
  <Point X="503" Y="245" T="1781630521216" />
  <Point X="513" Y="240" T="1781630521218" />
  <Point X="514" Y="239" T="1781630521219" />
  <Point X="522" Y="235" T="1781630521220" />
  <Point X="525" Y="234" T="1781630521221" />
  <Point X="526" Y="233" T="1781630521222" />
  <Point X="534" Y="229" T="1781630521223" />
  <Point X="537" Y="227" T="1781630521224" />
  <Point X="538" Y="227" T="1781630521225" />
  <Point X="546" Y="223" T="1781630521226" />
  <Point X="549" Y="221" T="1781630521227" />
  <Point X="550" Y="221" T="1781630521228" />
  <Point X="554" Y="219" T="1781630521230" />
  <Point X="561" Y="215" T="1781630521230" />
  <Point X="562" Y="215" T="1781630521231" />
  <Point X="566" Y="214" T="1781630521233" />
  <Point X="567" Y="213" T="1781630521235" />
  <Point X="579" Y="207" T="1781630521235" />
  <Point X="581" Y="206" T="1781630521236" />
  <Point X="587" Y="203" T="1781630521238" />
  <Point X="589" Y="202" T="1781630521238" />
  <Point X="592" Y="200" T="1781630521239" />
  <Point X="594" Y="200" T="1781630521240" />
  <Point X="595" Y="199" T="1781630521242" />
  <Point X="597" Y="198" T="1781630521243" />
  <Point X="609" Y="194" T="1781630521244" />
  <Point X="610" Y="192" T="1781630521245" />
  <Point X="612" Y="192" T="1781630521246" />
  <Point X="614" Y="191" T="1781630521247" />
  <Point X="615" Y="190" T="1781630521248" />
  <Point X="617" Y="190" T="1781630521249" />
  <Point X="619" Y="188" T="1781630521251" />
  <Point X="621" Y="188" T="1781630521252" />
  <Point X="625" Y="186" T="1781630521253" />
  <Point X="627" Y="185" T="1781630521254" />
  <Point X="627" Y="184" T="1781630521255" />
  <Point X="628" Y="184" T="1781630521257" />
  <Point X="638" Y="180" T="1781630521258" />
  <Point X="640" Y="179" T="1781630521259" />
  <Point X="641" Y="179" T="1781630521260" />
  <Point X="642" Y="178" T="1781630521261" />
  <Point X="645" Y="177" T="1781630521265" />
  <Point X="646" Y="176" T="1781630521266" />
  <Point X="655" Y="172" T="1781630521272" />
  <Point X="656" Y="172" T="1781630521272" />
  <Point X="657" Y="171" T="1781630521273" />
  <Point X="658" Y="171" T="1781630521275" />
  <Point X="658" Y="171" T="1781630521276" />
  <Point X="662" Y="170" T="1781630521277" />
  <Point X="663" Y="169" T="1781630521278" />
  <Point X="664" Y="168" T="1781630521281" />
  <Point X="665" Y="168" T="1781630521281" />
  <Point X="665" Y="168" T="1781630521282" />
  <Point X="667" Y="167" T="1781630521286" />
  <Point X="667" Y="166" T="1781630521286" />
  <Point X="669" Y="166" T="1781630521289" />
  <Point X="669" Y="166" T="1781630521289" />
  <Point X="670" Y="165" T="1781630521290" />
  <Point X="670" Y="165" T="1781630521291" />
  <Point X="671" Y="164" T="1781630521293" />
  <Point X="671" Y="164" T="1781630521294" />
  <Point X="672" Y="164" T="1781630521295" />
  <Point X="673" Y="163" T="1781630521297" />
  <Point X="673" Y="163" T="1781630521298" />
  <Point X="673" Y="163" T="1781630521299" />
  <Point X="673" Y="162" T="1781630521300" />
  <Point X="674" Y="162" T="1781630521302" />
  <Point X="674" Y="161" T="1781630521303" />
  <Point X="675" Y="161" T="1781630521305" />
  <Point X="675" Y="161" T="1781630521305" />
  <Point X="676" Y="161" T="1781630521306" />
  <Point X="676" Y="160" T="1781630521308" />
  <Point X="676" Y="160" T="1781630521309" />
  <Point X="676" Y="160" T="1781630521310" />
  <Point X="676" Y="159" T="1781630521311" />
  <Point X="677" Y="159" T="1781630521314" />
  <Point X="677" Y="159" T="1781630521314" />
  <Point X="677" Y="159" T="1781630521315" />
  <Point X="677" Y="159" T="1781630521316" />
  <Point X="678" Y="158" T="1781630521319" />
  <Point X="678" Y="158" T="1781630521323" />
  <Point X="678" Y="158" T="1781630521323" />
  <Point X="678" Y="157" T="1781630521324" />
  <Point X="678" Y="157" T="1781630521328" />
  <Point X="678" Y="157" T="1781630521328" />
  <Point X="678" Y="157" T="1781630521334" />
  <Point X="679" Y="157" T="1781630521339" />
  <Point X="679" Y="157" T="1781630521357" />
</Gesture>