<?xml version='1.0' encoding='utf-8'?>
<Gesture Name="pigtail" NumPts="434">
  <Point X="258" Y="431" T="1781630618092" />
  <Point X="258" Y="431" T="1781630618098" />
  <Point X="259" Y="431" T="1781630618106" />
  <Point X="259" Y="431" T="1781630618107" />
  <Point X="259" Y="431" T="1781630618108" />
  <Point X="260" Y="431" T="1781630618114" />
  <Point X="260" Y="431" T="1781630618117" />
  <Point X="260" Y="430" T="1781630618119" />
  <Point X="261" Y="430" T="1781630618122" />
  <Point X="261" Y="430" T="1781630618123" />
  <Point X="261" Y="430" T="1781630618124" />
  <Point X="262" Y="430" T="1781630618127" />
  <Point X="262" Y="429" T="1781630618128" />
  <Point X="263" Y="429" T="1781630618130" />
  <Point X="263" Y="429" T="1781630618131" />
  <Point X="263" Y="429" T="1781630618132" />
  <Point X="264" Y="429" T="1781630618135" />
  <Point X="264" Y="429" T="1781630618136" />
  <Point X="266" Y="428" T="1781630618140" />
  <Point X="266" Y="428" T="1781630618141" />
  <Point X="266" Y="428" T="1781630618142" />
  <Point X="267" Y="428" T="1781630618143" />
  <Point X="268" Y="427" T="1781630618144" />
  <Point X="268" Y="427" T="1781630618146" />
  <Point X="268" Y="427" T="1781630618147" />
  <Point X="269" Y="427" T="1781630618148" />
  <Point X="270" Y="427" T="1781630618149" />
  <Point X="270" Y="427" T="1781630618150" />
  <Point X="271" Y="427" T="1781630618152" />
  <Point X="272" Y="426" T="1781630618156" />
  <Point X="272" Y="426" T="1781630618156" />
  <Point X="273" Y="425" T="1781630618157" />
  <Point X="274" Y="425" T="1781630618158" />
  <Point X="274" Y="425" T="1781630618159" />
  <Point X="275" Y="425" T="1781630618160" />
  <Point X="275" Y="425" T="1781630618161" />
  <Point X="276" Y="424" T="1781630618163" />
  <Point X="277" Y="424" T="1781630618165" />
  <Point X="277" Y="424" T="1781630618166" />
  <Point X="279" Y="424" T="1781630618167" />
  <Point X="279" Y="423" T="1781630618168" />
  <Point X="280" Y="423" T="1781630618169" />
  <Point X="281" Y="422" T="1781630618171" />
  <Point X="282" Y="422" T="1781630618173" />
  <Point X="282" Y="422" T="1781630618174" />
  <Point X="283" Y="422" T="1781630618175" />
  <Point X="284" Y="422" T="1781630618176" />
  <Point X="284" Y="421" T="1781630618177" />
  <Point X="285" Y="421" T="1781630618178" />
  <Point X="285" Y="421" T="1781630618180" />
  <Point X="286" Y="421" T="1781630618181" />
  <Point X="287" Y="420" T="1781630618182" />
  <Point X="287" Y="420" T="1781630618183" />
  <Point X="288" Y="420" T="1781630618184" />
  <Point X="290" Y="419" T="1781630618185" />
  <Point X="291" Y="418" T="1781630618189" />
  <Point X="292" Y="418" T="1781630618189" />
  <Point X="292" Y="418" T="1781630618190" />
  <Point X="292" Y="418" T="1781630618191" />
  <Point X="293" Y="418" T="1781630618192" />
  <Point X="294" Y="417" T="1781630618193" />
  <Point X="294" Y="417" T="1781630618194" />
  <Point X="295" Y="417" T="1781630618196" />
  <Point X="296" Y="416" T="1781630618197" />
  <Point X="296" Y="416" T="1781630618198" />
  <Point X="297" Y="416" T="1781630618199" />
  <Point X="297" Y="416" T="1781630618200" />
  <Point X="298" Y="415" T="1781630618201" />
  <Point X="299" Y="415" T="1781630618202" />
  <Point X="299" Y="414" T="1781630618203" />
  <Point X="300" Y="414" T="1781630618204" />
  <Point X="301" Y="414" T="1781630618205" />
  <Point X="301" Y="413" T="1781630618206" />
  <Point X="302" Y="413" T="1781630618207" />
  <Point X="302" Y="413" T="1781630618208" />
  <Point X="303" Y="413" T="1781630618209" />
  <Point X="303" Y="412" T="1781630618210" />
  <Point X="304" Y="412" T="1781630618211" />
  <Point X="305" Y="411" T="1781630618213" />
  <Point X="306" Y="411" T="1781630618213" />
  <Point X="306" Y="411" T="1781630618214" />
  <Point X="307" Y="411" T="1781630618215" />
  <Point X="307" Y="410" T="1781630618216" />
  <Point X="308" Y="410" T="1781630618217" />
  <Point X="308" Y="410" T="1781630618218" />
  <Point X="308" Y="409" T="1781630618219" />
  <Point X="309" Y="409" T="1781630618220" />
  <Point X="310" Y="409" T="1781630618221" />
  <Point X="310" Y="408" T="1781630618222" />
  <Point X="311" Y="407" T="1781630618223" />
  <Point X="312" Y="407" T="1781630618224" />
  <Point X="312" Y="407" T="1781630618225" />
  <Point X="313" Y="406" T="1781630618226" />
  <Point X="313" Y="406" T="1781630618227" />
  <Point X="314" Y="406" T="1781630618228" />
  <Point X="314" Y="405" T="1781630618230" />
  <Point X="315" Y="405" T="1781630618230" />
  <Point X="316" Y="404" T="1781630618231" />
  <Point X="317" Y="403" T="1781630618232" />
  <Point X="318" Y="403" T="1781630618233" />
  <Point X="318" Y="402" T="1781630618234" />
  <Point X="319" Y="402" T="1781630618235" />
  <Point X="319" Y="401" T="1781630618236" />
  <Point X="321" Y="400" T="1781630618240" />
  <Point X="322" Y="400" T="1781630618240" />
  <Point X="322" Y="399" T="1781630618241" />
  <Point X="323" Y="399" T="1781630618242" />
  <Point X="323" Y="398" T="1781630618243" />
  <Point X="324" Y="398" T="1781630618244" />
  <Point X="325" Y="397" T="1781630618246" />
  <Point X="325" Y="396" T="1781630618247" />
  <Point X="326" Y="395" T="1781630618248" />
  <Point X="327" Y="395" T="1781630618249" />
  <Point X="327" Y="395" T="1781630618250" />
  <Point X="328" Y="394" T="1781630618251" />
  <Point X="328" Y="393" T="1781630618252" />
  <Point X="329" Y="393" T="1781630618253" />
  <Point X="329" Y="393" T="1781630618254" />
  <Point X="330" Y="392" T="1781630618255" />
  <Point X="330" Y="391" T="1781630618257" />
  <Point X="331" Y="391" T="1781630618257" />
  <Point X="331" Y="391" T="1781630618258" />
  <Point X="331" Y="391" T="1781630618259" />
  <Point X="333" Y="389" T="1781630618260" />
  <Point X="333" Y="388" T="1781630618261" />
  <Point X="334" Y="388" T="1781630618263" />
  <Point X="335" Y="387" T="1781630618264" />
  <Point X="335" Y="387" T="1781630618265" />
  <Point X="336" Y="386" T="1781630618266" />
  <Point X="336" Y="385" T="1781630618267" />
  <Point X="336" Y="385" T="1781630618268" />
  <Point X="337" Y="385" T="1781630618269" />
  <Point X="338" Y="383" T="1781630618271" />
  <Point X="338" Y="383" T="1781630618272" />
  <Point X="338" Y="383" T="1781630618273" />
  <Point X="339" Y="382" T="1781630618274" />
  <Point X="339" Y="382" T="1781630618275" />
  <Point X="340" Y="381" T="1781630618276" />
  <Point X="340" Y="381" T="1781630618277" />
  <Point X="340" Y="380" T="1781630618278" />
  <Point X="341" Y="379" T="1781630618280" />
  <Point X="342" Y="379" T="1781630618281" />
  <Point X="342" Y="379" T="1781630618282" />
  <Point X="342" Y="378" T="1781630618283" />
  <Point X="342" Y="378" T="1781630618284" />
  <Point X="343" Y="377" T="1781630618285" />
  <Point X="343" Y="377" T="1781630618286" />
  <Point X="344" Y="376" T="1781630618288" />
  <Point X="345" Y="375" T="1781630618290" />
  <Point X="345" Y="374" T="1781630618291" />
  <Point X="345" Y="374" T="1781630618292" />
  <Point X="345" Y="374" T="1781630618293" />
  <Point X="345" Y="373" T="1781630618294" />
  <Point X="346" Y="372" T="1781630618296" />
  <Point X="346" Y="372" T="1781630618297" />
  <Point X="347" Y="371" T="1781630618298" />
  <Point X="347" Y="371" T="1781630618299" />
  <Point X="347" Y="371" T="1781630618300" />
  <Point X="347" Y="370" T="1781630618301" />
  <Point X="347" Y="370" T="1781630618302" />
  <Point X="347" Y="370" T="1781630618303" />
  <Point X="347" Y="369" T="1781630618304" />
  <Point X="348" Y="369" T="1781630618305" />
  <Point X="348" Y="368" T="1781630618307" />
  <Point X="348" Y="367" T="1781630618308" />
  <Point X="348" Y="367" T="1781630618309" />
  <Point X="349" Y="367" T="1781630618310" />
  <Point X="349" Y="366" T="1781630618311" />
  <Point X="349" Y="365" T="1781630618313" />
  <Point X="349" Y="365" T="1781630618315" />
  <Point X="349" Y="365" T="1781630618316" />
  <Point X="349" Y="364" T="1781630618317" />
  <Point X="349" Y="364" T="1781630618318" />
  <Point X="349" Y="363" T="1781630618319" />
  <Point X="349" Y="363" T="1781630618320" />
  <Point X="349" Y="363" T="1781630618321" />
  <Point X="350" Y="363" T="1781630618322" />
  <Point X="350" Y="361" T="1781630618324" />
  <Point X="350" Y="361" T="1781630618325" />
  <Point X="350" Y="360" T="1781630618326" />
  <Point X="350" Y="360" T="1781630618327" />
  <Point X="350" Y="360" T="1781630618328" />
  <Point X="350" Y="359" T="1781630618330" />
  <Point X="350" Y="358" T="1781630618331" />
  <Point X="350" Y="358" T="1781630618332" />
  <Point X="351" Y="358" T="1781630618335" />
  <Point X="351" Y="357" T="1781630618336" />
  <Point X="351" Y="356" T="1781630618338" />
  <Point X="351" Y="356" T="1781630618339" />
  <Point X="351" Y="355" T="1781630618341" />
  <Point X="351" Y="355" T="1781630618342" />
  <Point X="351" Y="354" T="1781630618344" />
  <Point X="351" Y="354" T="1781630618346" />
  <Point X="351" Y="354" T="1781630618347" />
  <Point X="351" Y="353" T="1781630618350" />
  <Point X="351" Y="353" T="1781630618351" />
  <Point X="351" Y="352" T="1781630618352" />
  <Point X="351" Y="352" T="1781630618354" />
  <Point X="351" Y="351" T="1781630618355" />
  <Point X="351" Y="351" T="1781630618358" />
  <Point X="350" Y="351" T="1781630618359" />
  <Point X="350" Y="350" T="1781630618360" />
  <Point X="350" Y="350" T="1781630618363" />
  <Point X="350" Y="349" T="1781630618366" />
  <Point X="350" Y="349" T="1781630618367" />
  <Point X="350" Y="349" T="1781630618368" />
  <Point X="350" Y="349" T="1781630618371" />
  <Point X="349" Y="349" T="1781630618372" />
  <Point X="349" Y="348" T="1781630618375" />
  <Point X="349" Y="348" T="1781630618377" />
  <Point X="349" Y="347" T="1781630618383" />
  <Point X="349" Y="347" T="1781630618384" />
  <Point X="348" Y="347" T="1781630618393" />
  <Point X="348" Y="347" T="1781630618401" />
  <Point X="347" Y="347" T="1781630618405" />
  <Point X="347" Y="347" T="1781630618410" />
  <Point X="347" Y="347" T="1781630618413" />
  <Point X="346" Y="348" T="1781630618414" />
  <Point X="346" Y="348" T="1781630618417" />
  <Point X="345" Y="348" T="1781630618418" />
  <Point X="345" Y="349" T="1781630618421" />
  <Point X="344" Y="349" T="1781630618423" />
  <Point X="343" Y="349" T="1781630618426" />
  <Point X="343" Y="350" T="1781630618427" />
  <Point X="343" Y="350" T="1781630618428" />
  <Point X="343" Y="350" T="1781630618430" />
  <Point X="342" Y="351" T="1781630618431" />
  <Point X="342" Y="351" T="1781630618432" />
  <Point X="341" Y="351" T="1781630618433" />
  <Point X="341" Y="351" T="1781630618434" />
  <Point X="341" Y="351" T="1781630618435" />
  <Point X="341" Y="352" T="1781630618436" />
  <Point X="340" Y="352" T="1781630618438" />
  <Point X="339" Y="353" T="1781630618439" />
  <Point X="339" Y="353" T="1781630618440" />
  <Point X="338" Y="354" T="1781630618443" />
  <Point X="337" Y="354" T="1781630618444" />
  <Point X="336" Y="355" T="1781630618446" />
  <Point X="336" Y="355" T="1781630618447" />
  <Point X="335" Y="356" T="1781630618448" />
  <Point X="335" Y="356" T="1781630618449" />
  <Point X="334" Y="357" T="1781630618450" />
  <Point X="334" Y="357" T="1781630618451" />
  <Point X="334" Y="358" T="1781630618452" />
  <Point X="333" Y="358" T="1781630618453" />
  <Point X="333" Y="358" T="1781630618454" />
  <Point X="332" Y="359" T="1781630618455" />
  <Point X="332" Y="359" T="1781630618457" />
  <Point X="330" Y="360" T="1781630618460" />
  <Point X="330" Y="361" T="1781630618461" />
  <Point X="329" Y="362" T="1781630618463" />
  <Point X="328" Y="362" T="1781630618464" />
  <Point X="328" Y="363" T="1781630618465" />
  <Point X="328" Y="363" T="1781630618466" />
  <Point X="327" Y="364" T="1781630618467" />
  <Point X="327" Y="364" T="1781630618468" />
  <Point X="326" Y="364" T="1781630618469" />
  <Point X="326" Y="365" T="1781630618471" />
  <Point X="325" Y="366" T="1781630618472" />
  <Point X="324" Y="366" T="1781630618473" />
  <Point X="324" Y="367" T="1781630618474" />
  <Point X="323" Y="368" T="1781630618477" />
  <Point X="322" Y="369" T="1781630618478" />
  <Point X="321" Y="370" T="1781630618480" />
  <Point X="321" Y="371" T="1781630618481" />
  <Point X="321" Y="371" T="1781630618482" />
  <Point X="320" Y="371" T="1781630618483" />
  <Point X="320" Y="372" T="1781630618484" />
  <Point X="319" Y="373" T="1781630618485" />
  <Point X="319" Y="373" T="1781630618486" />
  <Point X="318" Y="375" T="1781630618488" />
  <Point X="318" Y="375" T="1781630618489" />
  <Point X="317" Y="376" T="1781630618490" />
  <Point X="317" Y="376" T="1781630618491" />
  <Point X="316" Y="378" T="1781630618494" />
  <Point X="315" Y="379" T="1781630618496" />
  <Point X="315" Y="380" T="1781630618497" />
  <Point X="314" Y="380" T="1781630618498" />
  <Point X="314" Y="381" T="1781630618499" />
  <Point X="314" Y="381" T="1781630618500" />
  <Point X="313" Y="382" T="1781630618501" />
  <Point X="313" Y="383" T="1781630618502" />
  <Point X="313" Y="383" T="1781630618503" />
  <Point X="312" Y="385" T="1781630618504" />
  <Point X="311" Y="385" T="1781630618505" />
  <Point X="311" Y="386" T="1781630618506" />
  <Point X="311" Y="387" T="1781630618507" />
  <Point X="311" Y="387" T="1781630618508" />
  <Point X="310" Y="388" T="1781630618511" />
  <Point X="309" Y="389" T="1781630618511" />
  <Point X="309" Y="390" T="1781630618513" />
  <Point X="309" Y="390" T="1781630618514" />
  <Point X="308" Y="391" T="1781630618515" />
  <Point X="308" Y="392" T="1781630618516" />
  <Point X="308" Y="393" T="1781630618517" />
  <Point X="307" Y="393" T="1781630618518" />
  <Point X="307" Y="393" T="1781630618519" />
  <Point X="307" Y="394" T="1781630618521" />
  <Point X="307" Y="395" T="1781630618521" />
  <Point X="306" Y="395" T="1781630618522" />
  <Point X="306" Y="396" T="1781630618523" />
  <Point X="306" Y="396" T="1781630618524" />
  <Point X="305" Y="398" T="1781630618527" />
  <Point X="305" Y="398" T="1781630618528" />
  <Point X="305" Y="399" T="1781630618530" />
  <Point X="305" Y="400" T="1781630618531" />
  <Point X="305" Y="400" T="1781630618532" />
  <Point X="305" Y="401" T="1781630618533" />
  <Point X="304" Y="401" T="1781630618534" />
  <Point X="304" Y="402" T="1781630618535" />
  <Point X="304" Y="402" T="1781630618536" />
  <Point X="304" Y="403" T="1781630618538" />
  <Point X="304" Y="403" T="1781630618539" />
  <Point X="304" Y="404" T="1781630618540" />
  <Point X="303" Y="404" T="1781630618541" />
  <Point X="303" Y="405" T="1781630618544" />
  <Point X="303" Y="406" T="1781630618545" />
  <Point X="303" Y="406" T="1781630618546" />
  <Point X="303" Y="406" T="1781630618547" />
  <Point X="303" Y="407" T="1781630618548" />
  <Point X="303" Y="407" T="1781630618549" />
  <Point X="303" Y="408" T="1781630618550" />
  <Point X="303" Y="408" T="1781630618551" />
  <Point X="303" Y="408" T="1781630618552" />
  <Point X="303" Y="409" T="1781630618553" />
  <Point X="303" Y="409" T="1781630618554" />
  <Point X="303" Y="410" T="1781630618555" />
  <Point X="303" Y="410" T="1781630618556" />
  <Point X="303" Y="410" T="1781630618557" />
  <Point X="304" Y="412" T="1781630618562" />
  <Point X="304" Y="412" T="1781630618563" />
  <Point X="304" Y="413" T="1781630618564" />
  <Point X="304" Y="413" T="1781630618565" />
  <Point X="304" Y="413" T="1781630618568" />
  <Point X="305" Y="413" T="1781630618569" />
  <Point X="305" Y="414" T="1781630618571" />
  <Point X="305" Y="415" T="1781630618572" />
  <Point X="305" Y="415" T="1781630618573" />
  <Point X="305" Y="415" T="1781630618575" />
  <Point X="307" Y="416" T="1781630618580" />
  <Point X="307" Y="417" T="1781630618582" />
  <Point X="307" Y="417" T="1781630618583" />
  <Point X="307" Y="417" T="1781630618584" />
  <Point X="308" Y="417" T="1781630618585" />
  <Point X="309" Y="418" T="1781630618588" />
  <Point X="309" Y="418" T="1781630618589" />
  <Point X="309" Y="418" T="1781630618590" />
  <Point X="310" Y="419" T="1781630618591" />
  <Point X="310" Y="419" T="1781630618592" />
  <Point X="311" Y="419" T="1781630618596" />
  <Point X="312" Y="420" T="1781630618597" />
  <Point X="312" Y="420" T="1781630618600" />
  <Point X="312" Y="420" T="1781630618601" />
  <Point X="313" Y="421" T="1781630618602" />
  <Point X="313" Y="421" T="1781630618603" />
  <Point X="314" Y="421" T="1781630618604" />
  <Point X="314" Y="421" T="1781630618605" />
  <Point X="314" Y="421" T="1781630618607" />
  <Point X="315" Y="421" T="1781630618608" />
  <Point X="315" Y="422" T="1781630618609" />
  <Point X="316" Y="422" T="1781630618613" />
  <Point X="317" Y="422" T="1781630618614" />
  <Point X="317" Y="423" T="1781630618615" />
  <Point X="318" Y="423" T="1781630618616" />
  <Point X="319" Y="423" T="1781630618617" />
  <Point X="319" Y="423" T="1781630618618" />
  <Point X="319" Y="423" T="1781630618619" />
  <Point X="320" Y="423" T="1781630618620" />
  <Point X="320" Y="423" T="1781630618621" />
  <Point X="321" Y="424" T="1781630618622" />
  <Point X="321" Y="424" T="1781630618623" />
  <Point X="321" Y="424" T="1781630618624" />
  <Point X="322" Y="424" T="1781630618625" />
  <Point X="324" Y="425" T="1781630618630" />
  <Point X="324" Y="425" T="1781630618631" />
  <Point X="325" Y="425" T="1781630618632" />
  <Point X="326" Y="425" T="1781630618633" />
  <Point X="326" Y="426" T="1781630618635" />
  <Point X="326" Y="426" T="1781630618636" />
  <Point X="328" Y="426" T="1781630618638" />
  <Point X="328" Y="426" T="1781630618639" />
  <Point X="328" Y="426" T="1781630618640" />
  <Point X="329" Y="426" T="1781630618641" />
  <Point X="329" Y="426" T="1781630618642" />
  <Point X="331" Y="427" T="1781630618646" />
  <Point X="332" Y="427" T="1781630618647" />
  <Point X="332" Y="427" T="1781630618648" />
  <Point X="332" Y="427" T="1781630618649" />
  <Point X="333" Y="427" T="1781630618650" />
  <Point X="334" Y="427" T="1781630618651" />
  <Point X="335" Y="427" T="1781630618652" />
  <Point X="335" Y="428" T="1781630618653" />
  <Point X="335" Y="428" T="1781630618654" />
  <Point X="336" Y="428" T="1781630618655" />
  <Point X="336" Y="428" T="1781630618656" />
  <Point X="337" Y="428" T="1781630618657" />
  <Point X="337" Y="428" T="1781630618658" />
  <Point X="338" Y="428" T="1781630618659" />
  <Point X="340" Y="428" T="1781630618663" />
  <Point X="340" Y="428" T="1781630618664" />
  <Point X="341" Y="428" T="1781630618665" />
  <Point X="342" Y="428" T="1781630618666" />
  <Point X="343" Y="428" T="1781630618667" />
  <Point X="343" Y="428" T="1781630618668" />
  <Point X="344" Y="428" T="1781630618669" />
  <Point X="345" Y="428" T="1781630618670" />
  <Point X="345" Y="428" T="1781630618671" />
  <Point X="345" Y="428" T="1781630618672" />
  <Point X="346" Y="428" T="1781630618673" />
  <Point X="347" Y="428" T="1781630618674" />
  <Point X="347" Y="428" T="1781630618675" />
  <Point X="347" Y="428" T="1781630618676" />
  <Point X="350" Y="428" T="1781630618680" />
  <Point X="351" Y="428" T="1781630618681" />
  <Point X="351" Y="428" T="1781630618683" />
  <Point X="352" Y="428" T="1781630618684" />
  <Point X="354" Y="428" T="1781630618685" />
  <Point X="354" Y="428" T="1781630618686" />
  <Point X="355" Y="428" T="1781630618688" />
  <Point X="356" Y="428" T="1781630618688" />
  <Point X="356" Y="428" T="1781630618689" />
  <Point X="357" Y="428" T="1781630618690" />
  <Point X="357" Y="428" T="1781630618691" />
  <Point X="358" Y="428" T="1781630618692" />
  <Point X="359" Y="428" T="1781630618693" />
  <Point X="361" Y="428" T="1781630618696" />
  <Point X="361" Y="427" T="1781630618697" />
  <Point X="361" Y="427" T="1781630618698" />
  <Point X="362" Y="427" T="1781630618699" />
  <Point X="363" Y="427" T="1781630618700" />
  <Point X="363" Y="427" T="1781630618702" />
  <Point X="365" Y="427" T="1781630618703" />
  <Point X="365" Y="427" T="1781630618704" />
  <Point X="365" Y="427" T="1781630618705" />
</Gesture>