<?xml version='1.0' encoding='utf-8'?>
<Gesture Name="right_curly_brace" NumPts="794">
  <Point X="335" Y="209" T="1781631781066" />
  <Point X="336" Y="209" T="1781631781066" />
  <Point X="336" Y="209" T="1781631781067" />
  <Point X="337" Y="208" T="1781631781070" />
  <Point X="337" Y="208" T="1781631781070" />
  <Point X="338" Y="208" T="1781631781071" />
  <Point X="339" Y="208" T="1781631781072" />
  <Point X="339" Y="208" T="1781631781073" />
  <Point X="339" Y="208" T="1781631781074" />
  <Point X="341" Y="208" T="1781631781077" />
  <Point X="341" Y="208" T="1781631781078" />
  <Point X="342" Y="208" T="1781631781079" />
  <Point X="343" Y="208" T="1781631781080" />
  <Point X="343" Y="207" T="1781631781081" />
  <Point X="344" Y="207" T="1781631781082" />
  <Point X="344" Y="207" T="1781631781083" />
  <Point X="345" Y="207" T="1781631781084" />
  <Point X="345" Y="207" T="1781631781086" />
  <Point X="346" Y="207" T="1781631781086" />
  <Point X="346" Y="207" T="1781631781087" />
  <Point X="347" Y="207" T="1781631781088" />
  <Point X="348" Y="207" T="1781631781089" />
  <Point X="348" Y="207" T="1781631781090" />
  <Point X="349" Y="207" T="1781631781091" />
  <Point X="350" Y="207" T="1781631781092" />
  <Point X="350" Y="207" T="1781631781093" />
  <Point X="350" Y="207" T="1781631781094" />
  <Point X="351" Y="207" T="1781631781095" />
  <Point X="352" Y="207" T="1781631781096" />
  <Point X="352" Y="207" T="1781631781097" />
  <Point X="353" Y="207" T="1781631781098" />
  <Point X="353" Y="207" T="1781631781099" />
  <Point X="354" Y="207" T="1781631781100" />
  <Point X="355" Y="207" T="1781631781102" />
  <Point X="356" Y="207" T="1781631781103" />
  <Point X="356" Y="207" T="1781631781104" />
  <Point X="357" Y="207" T="1781631781105" />
  <Point X="357" Y="207" T="1781631781106" />
  <Point X="358" Y="208" T="1781631781107" />
  <Point X="359" Y="208" T="1781631781109" />
  <Point X="359" Y="208" T="1781631781109" />
  <Point X="360" Y="208" T="1781631781110" />
  <Point X="360" Y="208" T="1781631781111" />
  <Point X="361" Y="208" T="1781631781112" />
  <Point X="361" Y="208" T="1781631781113" />
  <Point X="362" Y="208" T="1781631781114" />
  <Point X="362" Y="208" T="1781631781115" />
  <Point X="363" Y="208" T="1781631781116" />
  <Point X="364" Y="209" T="1781631781117" />
  <Point X="365" Y="209" T="1781631781119" />
  <Point X="365" Y="209" T="1781631781119" />
  <Point X="366" Y="209" T="1781631781120" />
  <Point X="366" Y="209" T="1781631781121" />
  <Point X="367" Y="210" T="1781631781123" />
  <Point X="368" Y="210" T="1781631781124" />
  <Point X="368" Y="210" T="1781631781126" />
  <Point X="369" Y="210" T="1781631781127" />
  <Point X="369" Y="210" T="1781631781127" />
  <Point X="370" Y="211" T="1781631781128" />
  <Point X="370" Y="211" T="1781631781129" />
  <Point X="371" Y="211" T="1781631781130" />
  <Point X="371" Y="211" T="1781631781131" />
  <Point X="372" Y="212" T="1781631781132" />
  <Point X="372" Y="212" T="1781631781133" />
  <Point X="373" Y="212" T="1781631781134" />
  <Point X="374" Y="213" T="1781631781137" />
  <Point X="375" Y="213" T="1781631781137" />
  <Point X="375" Y="213" T="1781631781138" />
  <Point X="375" Y="213" T="1781631781139" />
  <Point X="376" Y="214" T="1781631781140" />
  <Point X="377" Y="215" T="1781631781143" />
  <Point X="377" Y="215" T="1781631781144" />
  <Point X="378" Y="215" T="1781631781144" />
  <Point X="378" Y="215" T="1781631781145" />
  <Point X="379" Y="216" T="1781631781146" />
  <Point X="379" Y="216" T="1781631781147" />
  <Point X="380" Y="217" T="1781631781148" />
  <Point X="380" Y="217" T="1781631781149" />
  <Point X="381" Y="217" T="1781631781150" />
  <Point X="381" Y="218" T="1781631781153" />
  <Point X="382" Y="219" T="1781631781153" />
  <Point X="382" Y="219" T="1781631781154" />
  <Point X="383" Y="219" T="1781631781155" />
  <Point X="383" Y="220" T="1781631781156" />
  <Point X="384" Y="220" T="1781631781157" />
  <Point X="384" Y="221" T="1781631781159" />
  <Point X="384" Y="221" T="1781631781159" />
  <Point X="385" Y="221" T="1781631781161" />
  <Point X="385" Y="222" T="1781631781161" />
  <Point X="385" Y="223" T="1781631781162" />
  <Point X="386" Y="223" T="1781631781163" />
  <Point X="386" Y="223" T="1781631781165" />
  <Point X="386" Y="224" T="1781631781165" />
  <Point X="387" Y="224" T="1781631781166" />
  <Point X="387" Y="225" T="1781631781167" />
  <Point X="389" Y="228" T="1781631781171" />
  <Point X="389" Y="229" T="1781631781172" />
  <Point X="390" Y="229" T="1781631781173" />
  <Point X="390" Y="230" T="1781631781174" />
  <Point X="390" Y="231" T="1781631781176" />
  <Point X="390" Y="231" T="1781631781176" />
  <Point X="390" Y="232" T="1781631781177" />
  <Point X="391" Y="233" T="1781631781178" />
  <Point X="391" Y="233" T="1781631781179" />
  <Point X="391" Y="234" T="1781631781180" />
  <Point X="391" Y="235" T="1781631781181" />
  <Point X="392" Y="235" T="1781631781182" />
  <Point X="392" Y="236" T="1781631781183" />
  <Point X="392" Y="237" T="1781631781184" />
  <Point X="392" Y="237" T="1781631781186" />
  <Point X="392" Y="238" T="1781631781186" />
  <Point X="393" Y="239" T="1781631781187" />
  <Point X="393" Y="240" T="1781631781188" />
  <Point X="393" Y="241" T="1781631781189" />
  <Point X="393" Y="241" T="1781631781190" />
  <Point X="393" Y="243" T="1781631781192" />
  <Point X="393" Y="243" T="1781631781192" />
  <Point X="393" Y="245" T="1781631781195" />
  <Point X="393" Y="246" T="1781631781195" />
  <Point X="393" Y="247" T="1781631781196" />
  <Point X="393" Y="247" T="1781631781197" />
  <Point X="393" Y="248" T="1781631781198" />
  <Point X="393" Y="249" T="1781631781199" />
  <Point X="393" Y="251" T="1781631781200" />
  <Point X="393" Y="253" T="1781631781204" />
  <Point X="393" Y="255" T="1781631781204" />
  <Point X="393" Y="256" T="1781631781205" />
  <Point X="393" Y="257" T="1781631781206" />
  <Point X="393" Y="257" T="1781631781207" />
  <Point X="393" Y="258" T="1781631781209" />
  <Point X="393" Y="260" T="1781631781209" />
  <Point X="393" Y="263" T="1781631781211" />
  <Point X="392" Y="263" T="1781631781212" />
  <Point X="392" Y="265" T="1781631781213" />
  <Point X="392" Y="266" T="1781631781214" />
  <Point X="392" Y="267" T="1781631781215" />
  <Point X="392" Y="268" T="1781631781216" />
  <Point X="392" Y="269" T="1781631781217" />
  <Point X="391" Y="273" T="1781631781220" />
  <Point X="390" Y="276" T="1781631781221" />
  <Point X="390" Y="277" T="1781631781222" />
  <Point X="390" Y="279" T="1781631781223" />
  <Point X="389" Y="279" T="1781631781224" />
  <Point X="389" Y="282" T="1781631781227" />
  <Point X="388" Y="284" T="1781631781228" />
  <Point X="388" Y="285" T="1781631781229" />
  <Point X="388" Y="286" T="1781631781230" />
  <Point X="387" Y="288" T="1781631781231" />
  <Point X="387" Y="290" T="1781631781232" />
  <Point X="387" Y="291" T="1781631781233" />
  <Point X="386" Y="291" T="1781631781234" />
  <Point X="386" Y="294" T="1781631781237" />
  <Point X="385" Y="296" T="1781631781237" />
  <Point X="385" Y="298" T="1781631781238" />
  <Point X="385" Y="298" T="1781631781239" />
  <Point X="384" Y="300" T="1781631781240" />
  <Point X="384" Y="301" T="1781631781241" />
  <Point X="383" Y="302" T="1781631781242" />
  <Point X="383" Y="304" T="1781631781243" />
  <Point X="383" Y="304" T="1781631781245" />
  <Point X="382" Y="308" T="1781631781245" />
  <Point X="381" Y="310" T="1781631781246" />
  <Point X="381" Y="311" T="1781631781247" />
  <Point X="381" Y="311" T="1781631781248" />
  <Point X="380" Y="317" T="1781631781249" />
  <Point X="380" Y="317" T="1781631781250" />
  <Point X="378" Y="322" T="1781631781253" />
  <Point X="378" Y="323" T="1781631781253" />
  <Point X="377" Y="327" T="1781631781254" />
  <Point X="377" Y="327" T="1781631781255" />
  <Point X="377" Y="328" T="1781631781256" />
  <Point X="376" Y="330" T="1781631781257" />
  <Point X="376" Y="331" T="1781631781258" />
  <Point X="376" Y="333" T="1781631781259" />
  <Point X="375" Y="333" T="1781631781260" />
  <Point X="375" Y="335" T="1781631781262" />
  <Point X="375" Y="336" T="1781631781262" />
  <Point X="375" Y="337" T="1781631781263" />
  <Point X="374" Y="339" T="1781631781264" />
  <Point X="374" Y="340" T="1781631781265" />
  <Point X="373" Y="341" T="1781631781266" />
  <Point X="373" Y="343" T="1781631781267" />
  <Point X="373" Y="345" T="1781631781270" />
  <Point X="372" Y="346" T="1781631781270" />
  <Point X="372" Y="348" T="1781631781271" />
  <Point X="372" Y="349" T="1781631781272" />
  <Point X="371" Y="350" T="1781631781273" />
  <Point X="371" Y="352" T="1781631781274" />
  <Point X="371" Y="353" T="1781631781275" />
  <Point X="370" Y="356" T="1781631781276" />
  <Point X="369" Y="358" T="1781631781279" />
  <Point X="369" Y="360" T="1781631781279" />
  <Point X="369" Y="361" T="1781631781280" />
  <Point X="369" Y="361" T="1781631781281" />
  <Point X="369" Y="362" T="1781631781282" />
  <Point X="369" Y="364" T="1781631781283" />
  <Point X="369" Y="364" T="1781631781284" />
  <Point X="368" Y="366" T="1781631781286" />
  <Point X="368" Y="367" T="1781631781286" />
  <Point X="368" Y="368" T="1781631781287" />
  <Point X="368" Y="369" T="1781631781288" />
  <Point X="368" Y="369" T="1781631781289" />
  <Point X="367" Y="371" T="1781631781290" />
  <Point X="367" Y="373" T="1781631781292" />
  <Point X="367" Y="374" T="1781631781293" />
  <Point X="367" Y="376" T="1781631781296" />
  <Point X="366" Y="377" T="1781631781296" />
  <Point X="366" Y="381" T="1781631781297" />
  <Point X="366" Y="382" T="1781631781298" />
  <Point X="366" Y="382" T="1781631781299" />
  <Point X="366" Y="384" T="1781631781300" />
  <Point X="366" Y="388" T="1781631781304" />
  <Point X="366" Y="389" T="1781631781305" />
  <Point X="366" Y="393" T="1781631781307" />
  <Point X="366" Y="394" T="1781631781309" />
  <Point X="366" Y="395" T="1781631781309" />
  <Point X="366" Y="396" T="1781631781310" />
  <Point X="366" Y="397" T="1781631781312" />
  <Point X="366" Y="398" T="1781631781313" />
  <Point X="366" Y="401" T="1781631781314" />
  <Point X="366" Y="402" T="1781631781315" />
  <Point X="366" Y="403" T="1781631781316" />
  <Point X="366" Y="404" T="1781631781317" />
  <Point X="366" Y="405" T="1781631781318" />
  <Point X="366" Y="405" T="1781631781320" />
  <Point X="366" Y="407" T="1781631781320" />
  <Point X="366" Y="408" T="1781631781321" />
  <Point X="366" Y="408" T="1781631781322" />
  <Point X="366" Y="409" T="1781631781323" />
  <Point X="366" Y="410" T="1781631781324" />
  <Point X="366" Y="410" T="1781631781325" />
  <Point X="366" Y="411" T="1781631781326" />
  <Point X="366" Y="412" T="1781631781327" />
  <Point X="367" Y="414" T="1781631781329" />
  <Point X="367" Y="414" T="1781631781330" />
  <Point X="368" Y="418" T="1781631781331" />
  <Point X="368" Y="418" T="1781631781332" />
  <Point X="368" Y="419" T="1781631781333" />
  <Point X="368" Y="420" T="1781631781334" />
  <Point X="369" Y="420" T="1781631781336" />
  <Point X="369" Y="422" T="1781631781336" />
  <Point X="370" Y="423" T="1781631781337" />
  <Point X="370" Y="423" T="1781631781338" />
  <Point X="370" Y="424" T="1781631781339" />
  <Point X="370" Y="425" T="1781631781340" />
  <Point X="371" Y="426" T="1781631781342" />
  <Point X="371" Y="427" T="1781631781343" />
  <Point X="372" Y="429" T="1781631781346" />
  <Point X="373" Y="429" T="1781631781347" />
  <Point X="373" Y="430" T="1781631781348" />
  <Point X="374" Y="430" T="1781631781349" />
  <Point X="374" Y="431" T="1781631781350" />
  <Point X="375" Y="432" T="1781631781353" />
  <Point X="376" Y="433" T="1781631781353" />
  <Point X="376" Y="433" T="1781631781354" />
  <Point X="376" Y="434" T="1781631781355" />
  <Point X="377" Y="434" T="1781631781356" />
  <Point X="378" Y="435" T="1781631781357" />
  <Point X="378" Y="435" T="1781631781359" />
  <Point X="378" Y="436" T="1781631781359" />
  <Point X="379" Y="436" T="1781631781360" />
  <Point X="380" Y="437" T="1781631781363" />
  <Point X="381" Y="437" T="1781631781364" />
  <Point X="382" Y="438" T="1781631781365" />
  <Point X="382" Y="438" T="1781631781366" />
  <Point X="383" Y="438" T="1781631781367" />
  <Point X="384" Y="439" T="1781631781369" />
  <Point X="385" Y="439" T="1781631781370" />
  <Point X="385" Y="439" T="1781631781371" />
  <Point X="385" Y="440" T="1781631781372" />
  <Point X="386" Y="440" T="1781631781374" />
  <Point X="387" Y="440" T="1781631781374" />
  <Point X="389" Y="441" T="1781631781377" />
  <Point X="389" Y="441" T="1781631781377" />
  <Point X="391" Y="441" T="1781631781380" />
  <Point X="392" Y="441" T="1781631781381" />
  <Point X="393" Y="442" T="1781631781382" />
  <Point X="393" Y="442" T="1781631781383" />
  <Point X="395" Y="442" T="1781631781387" />
  <Point X="396" Y="443" T="1781631781388" />
  <Point X="397" Y="443" T="1781631781389" />
  <Point X="398" Y="443" T="1781631781390" />
  <Point X="399" Y="443" T="1781631781392" />
  <Point X="400" Y="443" T="1781631781393" />
  <Point X="401" Y="443" T="1781631781394" />
  <Point X="402" Y="443" T="1781631781397" />
  <Point X="402" Y="443" T="1781631781397" />
  <Point X="403" Y="443" T="1781631781398" />
  <Point X="404" Y="443" T="1781631781399" />
  <Point X="404" Y="443" T="1781631781400" />
  <Point X="406" Y="443" T="1781631781403" />
  <Point X="407" Y="443" T="1781631781403" />
  <Point X="408" Y="443" T="1781631781404" />
  <Point X="409" Y="443" T="1781631781405" />
  <Point X="410" Y="443" T="1781631781406" />
  <Point X="410" Y="443" T="1781631781407" />
  <Point X="411" Y="443" T="1781631781409" />
  <Point X="412" Y="443" T="1781631781409" />
  <Point X="412" Y="443" T="1781631781410" />
  <Point X="413" Y="443" T="1781631781411" />
  <Point X="414" Y="443" T="1781631781414" />
  <Point X="415" Y="443" T="1781631781414" />
  <Point X="416" Y="443" T="1781631781415" />
  <Point X="416" Y="443" T="1781631781416" />
  <Point X="417" Y="442" T="1781631781417" />
  <Point X="421" Y="442" T="1781631781419" />
  <Point X="422" Y="442" T="1781631781420" />
  <Point X="423" Y="441" T="1781631781421" />
  <Point X="424" Y="441" T="1781631781423" />
  <Point X="425" Y="441" T="1781631781424" />
  <Point X="428" Y="440" T="1781631781427" />
  <Point X="430" Y="439" T="1781631781431" />
  <Point X="431" Y="439" T="1781631781431" />
  <Point X="431" Y="439" T="1781631781432" />
  <Point X="432" Y="439" T="1781631781433" />
  <Point X="432" Y="438" T="1781631781434" />
  <Point X="433" Y="438" T="1781631781436" />
  <Point X="434" Y="438" T="1781631781436" />
  <Point X="434" Y="438" T="1781631781437" />
  <Point X="435" Y="437" T="1781631781438" />
  <Point X="436" Y="437" T="1781631781439" />
  <Point X="436" Y="437" T="1781631781440" />
  <Point X="437" Y="436" T="1781631781442" />
  <Point X="437" Y="436" T="1781631781442" />
  <Point X="438" Y="435" T="1781631781443" />
  <Point X="438" Y="435" T="1781631781444" />
  <Point X="440" Y="434" T="1781631781448" />
  <Point X="441" Y="433" T="1781631781448" />
  <Point X="441" Y="433" T="1781631781449" />
  <Point X="442" Y="433" T="1781631781450" />
  <Point X="442" Y="433" T="1781631781451" />
  <Point X="443" Y="432" T="1781631781453" />
  <Point X="443" Y="432" T="1781631781453" />
  <Point X="444" Y="431" T="1781631781454" />
  <Point X="444" Y="431" T="1781631781455" />
  <Point X="445" Y="430" T="1781631781456" />
  <Point X="445" Y="429" T="1781631781457" />
  <Point X="446" Y="429" T="1781631781459" />
  <Point X="446" Y="429" T="1781631781459" />
  <Point X="447" Y="428" T="1781631781460" />
  <Point X="447" Y="428" T="1781631781461" />
  <Point X="448" Y="426" T="1781631781465" />
  <Point X="449" Y="426" T="1781631781465" />
  <Point X="449" Y="425" T="1781631781466" />
  <Point X="449" Y="425" T="1781631781467" />
  <Point X="449" Y="424" T="1781631781469" />
  <Point X="450" Y="424" T="1781631781470" />
  <Point X="450" Y="423" T="1781631781471" />
  <Point X="451" Y="422" T="1781631781472" />
  <Point X="451" Y="422" T="1781631781473" />
  <Point X="452" Y="421" T="1781631781474" />
  <Point X="452" Y="421" T="1781631781475" />
  <Point X="452" Y="420" T="1781631781476" />
  <Point X="452" Y="420" T="1781631781477" />
  <Point X="452" Y="419" T="1781631781478" />
  <Point X="453" Y="417" T="1781631781482" />
  <Point X="453" Y="417" T="1781631781482" />
  <Point X="453" Y="417" T="1781631781483" />
  <Point X="453" Y="416" T="1781631781484" />
  <Point X="453" Y="415" T="1781631781486" />
  <Point X="454" Y="415" T="1781631781486" />
  <Point X="454" Y="415" T="1781631781487" />
  <Point X="454" Y="414" T="1781631781488" />
  <Point X="454" Y="413" T="1781631781489" />
  <Point X="454" Y="413" T="1781631781490" />
  <Point X="454" Y="412" T="1781631781492" />
  <Point X="454" Y="412" T="1781631781493" />
  <Point X="454" Y="411" T="1781631781494" />
  <Point X="454" Y="411" T="1781631781495" />
  <Point X="454" Y="409" T="1781631781499" />
  <Point X="454" Y="409" T="1781631781499" />
  <Point X="454" Y="408" T="1781631781500" />
  <Point X="454" Y="408" T="1781631781503" />
  <Point X="454" Y="407" T="1781631781503" />
  <Point X="454" Y="407" T="1781631781504" />
  <Point X="454" Y="406" T="1781631781505" />
  <Point X="453" Y="406" T="1781631781506" />
  <Point X="453" Y="406" T="1781631781507" />
  <Point X="453" Y="405" T="1781631781509" />
  <Point X="453" Y="405" T="1781631781510" />
  <Point X="453" Y="404" T="1781631781511" />
  <Point X="452" Y="404" T="1781631781512" />
  <Point X="452" Y="403" T="1781631781515" />
  <Point X="452" Y="403" T="1781631781515" />
  <Point X="452" Y="402" T="1781631781516" />
  <Point X="452" Y="401" T="1781631781520" />
  <Point X="452" Y="401" T="1781631781520" />
  <Point X="452" Y="401" T="1781631781521" />
  <Point X="452" Y="401" T="1781631781522" />
  <Point X="451" Y="400" T="1781631781524" />
  <Point X="451" Y="400" T="1781631781526" />
  <Point X="451" Y="399" T="1781631781527" />
  <Point X="450" Y="399" T="1781631781533" />
  <Point X="450" Y="399" T="1781631781534" />
  <Point X="450" Y="398" T="1781631781536" />
  <Point X="450" Y="398" T="1781631781537" />
  <Point X="450" Y="398" T="1781631781538" />
  <Point X="449" Y="397" T="1781631781540" />
  <Point X="449" Y="397" T="1781631781543" />
  <Point X="448" Y="397" T="1781631781550" />
  <Point X="447" Y="396" T="1781631781553" />
  <Point X="447" Y="396" T="1781631781553" />
  <Point X="447" Y="396" T="1781631781555" />
  <Point X="447" Y="396" T="1781631781556" />
  <Point X="446" Y="396" T="1781631781557" />
  <Point X="446" Y="395" T="1781631781559" />
  <Point X="446" Y="395" T="1781631781560" />
  <Point X="445" Y="395" T="1781631781561" />
  <Point X="444" Y="395" T="1781631781566" />
  <Point X="444" Y="395" T="1781631781567" />
  <Point X="443" Y="395" T="1781631781569" />
  <Point X="443" Y="395" T="1781631781570" />
  <Point X="443" Y="395" T="1781631781571" />
  <Point X="442" Y="395" T="1781631781573" />
  <Point X="442" Y="395" T="1781631781574" />
  <Point X="441" Y="395" T="1781631781575" />
  <Point X="441" Y="395" T="1781631781576" />
  <Point X="441" Y="395" T="1781631781578" />
  <Point X="440" Y="395" T="1781631781579" />
  <Point X="439" Y="394" T="1781631781583" />
  <Point X="438" Y="394" T="1781631781584" />
  <Point X="437" Y="394" T="1781631781585" />
  <Point X="437" Y="394" T="1781631781587" />
  <Point X="437" Y="394" T="1781631781587" />
  <Point X="436" Y="394" T="1781631781588" />
  <Point X="436" Y="394" T="1781631781589" />
  <Point X="435" Y="394" T="1781631781590" />
  <Point X="434" Y="394" T="1781631781592" />
  <Point X="434" Y="394" T="1781631781592" />
  <Point X="433" Y="395" T="1781631781594" />
  <Point X="433" Y="395" T="1781631781595" />
  <Point X="431" Y="395" T="1781631781596" />
  <Point X="430" Y="395" T="1781631781600" />
  <Point X="429" Y="395" T="1781631781600" />
  <Point X="429" Y="395" T="1781631781603" />
  <Point X="428" Y="396" T="1781631781603" />
  <Point X="427" Y="396" T="1781631781604" />
  <Point X="426" Y="396" T="1781631781605" />
  <Point X="425" Y="397" T="1781631781607" />
  <Point X="424" Y="397" T="1781631781609" />
  <Point X="424" Y="397" T="1781631781609" />
  <Point X="423" Y="398" T="1781631781610" />
  <Point X="422" Y="398" T="1781631781612" />
  <Point X="422" Y="398" T="1781631781613" />
  <Point X="420" Y="400" T="1781631781617" />
  <Point X="417" Y="401" T="1781631781619" />
  <Point X="417" Y="401" T="1781631781620" />
  <Point X="416" Y="401" T="1781631781621" />
  <Point X="416" Y="402" T="1781631781622" />
  <Point X="415" Y="402" T="1781631781623" />
  <Point X="415" Y="403" T="1781631781624" />
  <Point X="414" Y="403" T="1781631781625" />
  <Point X="414" Y="403" T="1781631781627" />
  <Point X="413" Y="404" T="1781631781628" />
  <Point X="412" Y="405" T="1781631781629" />
  <Point X="412" Y="405" T="1781631781630" />
  <Point X="410" Y="407" T="1781631781634" />
  <Point X="410" Y="407" T="1781631781634" />
  <Point X="409" Y="408" T="1781631781636" />
  <Point X="408" Y="408" T="1781631781637" />
  <Point X="407" Y="410" T="1781631781638" />
  <Point X="407" Y="411" T="1781631781639" />
  <Point X="406" Y="411" T="1781631781640" />
  <Point X="405" Y="413" T="1781631781642" />
  <Point X="405" Y="413" T="1781631781643" />
  <Point X="404" Y="414" T="1781631781645" />
  <Point X="404" Y="414" T="1781631781646" />
  <Point X="402" Y="418" T="1781631781651" />
  <Point X="401" Y="420" T="1781631781653" />
  <Point X="400" Y="421" T="1781631781654" />
  <Point X="400" Y="422" T="1781631781655" />
  <Point X="400" Y="423" T="1781631781656" />
  <Point X="399" Y="423" T="1781631781657" />
  <Point X="399" Y="424" T="1781631781659" />
  <Point X="399" Y="425" T="1781631781659" />
  <Point X="398" Y="425" T="1781631781660" />
  <Point X="398" Y="426" T="1781631781661" />
  <Point X="398" Y="426" T="1781631781662" />
  <Point X="398" Y="427" T="1781631781663" />
  <Point X="397" Y="430" T="1781631781667" />
  <Point X="397" Y="431" T="1781631781669" />
  <Point X="396" Y="431" T="1781631781670" />
  <Point X="396" Y="433" T="1781631781671" />
  <Point X="396" Y="433" T="1781631781672" />
  <Point X="396" Y="434" T="1781631781673" />
  <Point X="396" Y="435" T="1781631781674" />
  <Point X="396" Y="435" T="1781631781675" />
  <Point X="396" Y="436" T="1781631781676" />
  <Point X="396" Y="436" T="1781631781677" />
  <Point X="396" Y="437" T="1781631781678" />
  <Point X="396" Y="438" T="1781631781679" />
  <Point X="396" Y="438" T="1781631781680" />
  <Point X="395" Y="441" T="1781631781684" />
  <Point X="395" Y="441" T="1781631781686" />
  <Point X="395" Y="442" T="1781631781687" />
  <Point X="395" Y="443" T="1781631781688" />
  <Point X="395" Y="443" T="1781631781689" />
  <Point X="395" Y="444" T="1781631781690" />
  <Point X="395" Y="445" T="1781631781692" />
  <Point X="395" Y="446" T="1781631781693" />
  <Point X="395" Y="446" T="1781631781694" />
  <Point X="395" Y="446" T="1781631781696" />
  <Point X="395" Y="447" T="1781631781697" />
  <Point X="396" Y="450" T="1781631781701" />
  <Point X="396" Y="451" T="1781631781703" />
  <Point X="396" Y="452" T="1781631781703" />
  <Point X="396" Y="452" T="1781631781704" />
  <Point X="396" Y="453" T="1781631781705" />
  <Point X="396" Y="453" T="1781631781706" />
  <Point X="396" Y="454" T="1781631781707" />
  <Point X="396" Y="454" T="1781631781709" />
  <Point X="397" Y="455" T="1781631781709" />
  <Point X="397" Y="455" T="1781631781710" />
  <Point X="397" Y="456" T="1781631781711" />
  <Point X="397" Y="456" T="1781631781712" />
  <Point X="397" Y="457" T="1781631781713" />
  <Point X="398" Y="457" T="1781631781714" />
  <Point X="398" Y="459" T="1781631781718" />
  <Point X="399" Y="460" T="1781631781720" />
  <Point X="399" Y="461" T="1781631781720" />
  <Point X="399" Y="462" T="1781631781721" />
  <Point X="399" Y="462" T="1781631781722" />
  <Point X="400" Y="462" T="1781631781723" />
  <Point X="400" Y="463" T="1781631781724" />
  <Point X="400" Y="464" T="1781631781726" />
  <Point X="401" Y="464" T="1781631781726" />
  <Point X="401" Y="465" T="1781631781727" />
  <Point X="401" Y="466" T="1781631781729" />
  <Point X="401" Y="466" T="1781631781730" />
  <Point X="402" Y="468" T="1781631781734" />
  <Point X="403" Y="469" T="1781631781734" />
  <Point X="403" Y="470" T="1781631781736" />
  <Point X="403" Y="470" T="1781631781737" />
  <Point X="403" Y="471" T="1781631781738" />
  <Point X="404" Y="472" T="1781631781739" />
  <Point X="404" Y="472" T="1781631781740" />
  <Point X="404" Y="473" T="1781631781741" />
  <Point X="404" Y="473" T="1781631781742" />
  <Point X="405" Y="474" T="1781631781743" />
  <Point X="405" Y="475" T="1781631781744" />
  <Point X="405" Y="475" T="1781631781745" />
  <Point X="406" Y="476" T="1781631781746" />
  <Point X="406" Y="477" T="1781631781747" />
  <Point X="407" Y="479" T="1781631781751" />
  <Point X="407" Y="479" T="1781631781751" />
  <Point X="407" Y="480" T="1781631781753" />
  <Point X="408" Y="481" T="1781631781753" />
  <Point X="408" Y="481" T="1781631781754" />
  <Point X="409" Y="483" T="1781631781755" />
  <Point X="409" Y="484" T="1781631781756" />
  <Point X="409" Y="484" T="1781631781757" />
  <Point X="409" Y="485" T="1781631781759" />
  <Point X="410" Y="487" T="1781631781759" />
  <Point X="410" Y="487" T="1781631781760" />
  <Point X="410" Y="488" T="1781631781761" />
  <Point X="411" Y="489" T="1781631781762" />
  <Point X="411" Y="490" T="1781631781763" />
  <Point X="411" Y="491" T="1781631781764" />
  <Point X="413" Y="495" T="1781631781769" />
  <Point X="413" Y="496" T="1781631781770" />
  <Point X="413" Y="497" T="1781631781771" />
  <Point X="414" Y="498" T="1781631781772" />
  <Point X="414" Y="498" T="1781631781773" />
  <Point X="414" Y="499" T="1781631781774" />
  <Point X="414" Y="500" T="1781631781776" />
  <Point X="415" Y="500" T="1781631781776" />
  <Point X="415" Y="502" T="1781631781777" />
  <Point X="415" Y="503" T="1781631781778" />
  <Point X="416" Y="503" T="1781631781779" />
  <Point X="416" Y="504" T="1781631781780" />
  <Point X="416" Y="505" T="1781631781781" />
  <Point X="417" Y="507" T="1781631781786" />
  <Point X="417" Y="508" T="1781631781786" />
  <Point X="418" Y="509" T="1781631781787" />
  <Point X="418" Y="510" T="1781631781788" />
  <Point X="418" Y="510" T="1781631781789" />
  <Point X="418" Y="511" T="1781631781790" />
  <Point X="418" Y="512" T="1781631781792" />
  <Point X="418" Y="512" T="1781631781792" />
  <Point X="419" Y="513" T="1781631781793" />
  <Point X="419" Y="514" T="1781631781794" />
  <Point X="419" Y="514" T="1781631781795" />
  <Point X="419" Y="515" T="1781631781796" />
  <Point X="419" Y="517" T="1781631781797" />
  <Point X="420" Y="520" T="1781631781803" />
  <Point X="420" Y="520" T="1781631781803" />
  <Point X="420" Y="521" T="1781631781804" />
  <Point X="420" Y="522" T="1781631781805" />
  <Point X="420" Y="522" T="1781631781806" />
  <Point X="420" Y="523" T="1781631781807" />
  <Point X="421" Y="523" T="1781631781809" />
  <Point X="421" Y="525" T="1781631781809" />
  <Point X="421" Y="526" T="1781631781810" />
  <Point X="421" Y="527" T="1781631781811" />
  <Point X="421" Y="527" T="1781631781812" />
  <Point X="421" Y="528" T="1781631781813" />
  <Point X="421" Y="528" T="1781631781814" />
  <Point X="421" Y="531" T="1781631781819" />
  <Point X="421" Y="532" T="1781631781820" />
  <Point X="422" Y="533" T="1781631781821" />
  <Point X="422" Y="533" T="1781631781822" />
  <Point X="422" Y="534" T="1781631781823" />
  <Point X="422" Y="535" T="1781631781824" />
  <Point X="422" Y="535" T="1781631781825" />
  <Point X="422" Y="536" T="1781631781826" />
  <Point X="422" Y="537" T="1781631781827" />
  <Point X="422" Y="537" T="1781631781828" />
  <Point X="422" Y="538" T="1781631781829" />
  <Point X="422" Y="539" T="1781631781830" />
  <Point X="422" Y="539" T="1781631781831" />
  <Point X="422" Y="541" T="1781631781836" />
  <Point X="422" Y="542" T="1781631781836" />
  <Point X="422" Y="543" T="1781631781837" />
  <Point X="422" Y="544" T="1781631781839" />
  <Point X="422" Y="545" T="1781631781840" />
  <Point X="422" Y="547" T="1781631781842" />
  <Point X="422" Y="547" T="1781631781843" />
  <Point X="422" Y="548" T="1781631781844" />
  <Point X="422" Y="548" T="1781631781845" />
  <Point X="421" Y="549" T="1781631781846" />
  <Point X="421" Y="549" T="1781631781847" />
  <Point X="421" Y="550" T="1781631781848" />
  <Point X="420" Y="553" T="1781631781853" />
  <Point X="420" Y="554" T="1781631781853" />
  <Point X="420" Y="554" T="1781631781854" />
  <Point X="420" Y="555" T="1781631781855" />
  <Point X="420" Y="556" T="1781631781856" />
  <Point X="419" Y="556" T="1781631781857" />
  <Point X="419" Y="557" T="1781631781859" />
  <Point X="419" Y="557" T="1781631781859" />
  <Point X="419" Y="558" T="1781631781860" />
  <Point X="419" Y="558" T="1781631781861" />
  <Point X="419" Y="559" T="1781631781862" />
  <Point X="418" Y="559" T="1781631781863" />
  <Point X="418" Y="560" T="1781631781864" />
  <Point X="418" Y="561" T="1781631781865" />
  <Point X="417" Y="563" T="1781631781869" />
  <Point X="416" Y="564" T="1781631781869" />
  <Point X="416" Y="564" T="1781631781870" />
  <Point X="416" Y="564" T="1781631781871" />
  <Point X="416" Y="565" T="1781631781872" />
  <Point X="414" Y="567" T="1781631781873" />
  <Point X="414" Y="567" T="1781631781874" />
  <Point X="414" Y="567" T="1781631781875" />
  <Point X="413" Y="568" T="1781631781876" />
  <Point X="413" Y="569" T="1781631781877" />
  <Point X="412" Y="569" T="1781631781878" />
  <Point X="412" Y="569" T="1781631781879" />
  <Point X="412" Y="570" T="1781631781880" />
  <Point X="412" Y="570" T="1781631781881" />
  <Point X="409" Y="573" T="1781631781886" />
  <Point X="408" Y="573" T="1781631781887" />
  <Point X="408" Y="573" T="1781631781888" />
  <Point X="407" Y="574" T="1781631781889" />
  <Point X="407" Y="574" T="1781631781890" />
  <Point X="406" Y="575" T="1781631781892" />
  <Point X="406" Y="575" T="1781631781893" />
  <Point X="405" Y="576" T="1781631781894" />
  <Point X="405" Y="576" T="1781631781895" />
  <Point X="404" Y="576" T="1781631781896" />
  <Point X="404" Y="576" T="1781631781897" />
  <Point X="403" Y="577" T="1781631781898" />
  <Point X="401" Y="578" T="1781631781903" />
  <Point X="400" Y="578" T="1781631781903" />
  <Point X="399" Y="578" T="1781631781904" />
  <Point X="399" Y="579" T="1781631781905" />
  <Point X="398" Y="579" T="1781631781906" />
  <Point X="398" Y="579" T="1781631781907" />
  <Point X="397" Y="579" T="1781631781909" />
  <Point X="396" Y="580" T="1781631781909" />
  <Point X="396" Y="580" T="1781631781910" />
  <Point X="395" Y="580" T="1781631781911" />
  <Point X="394" Y="580" T="1781631781912" />
  <Point X="394" Y="580" T="1781631781913" />
  <Point X="393" Y="580" T="1781631781914" />
  <Point X="392" Y="581" T="1781631781915" />
  <Point X="390" Y="581" T="1781631781919" />
  <Point X="390" Y="581" T="1781631781920" />
  <Point X="389" Y="581" T="1781631781921" />
  <Point X="387" Y="581" T="1781631781922" />
  <Point X="386" Y="582" T="1781631781923" />
  <Point X="385" Y="582" T="1781631781924" />
  <Point X="385" Y="582" T="1781631781925" />
  <Point X="384" Y="582" T="1781631781926" />
  <Point X="383" Y="582" T="1781631781927" />
  <Point X="382" Y="582" T="1781631781928" />
  <Point X="382" Y="582" T="1781631781929" />
  <Point X="381" Y="582" T="1781631781930" />
  <Point X="380" Y="582" T="1781631781931" />
  <Point X="380" Y="582" T="1781631781932" />
  <Point X="377" Y="582" T="1781631781937" />
  <Point X="376" Y="582" T="1781631781937" />
  <Point X="376" Y="582" T="1781631781938" />
  <Point X="375" Y="582" T="1781631781939" />
  <Point X="373" Y="582" T="1781631781940" />
  <Point X="371" Y="582" T="1781631781942" />
  <Point X="371" Y="582" T="1781631781943" />
  <Point X="370" Y="582" T="1781631781944" />
  <Point X="369" Y="582" T="1781631781945" />
  <Point X="369" Y="582" T="1781631781946" />
  <Point X="367" Y="582" T="1781631781947" />
  <Point X="366" Y="582" T="1781631781948" />
  <Point X="366" Y="582" T="1781631781949" />
  <Point X="363" Y="582" T="1781631781953" />
  <Point X="362" Y="582" T="1781631781954" />
  <Point X="360" Y="582" T="1781631781955" />
  <Point X="360" Y="581" T="1781631781956" />
  <Point X="360" Y="581" T="1781631781957" />
  <Point X="359" Y="581" T="1781631781959" />
  <Point X="358" Y="581" T="1781631781959" />
  <Point X="358" Y="581" T="1781631781960" />
  <Point X="357" Y="580" T="1781631781961" />
  <Point X="356" Y="580" T="1781631781962" />
  <Point X="356" Y="580" T="1781631781963" />
  <Point X="355" Y="580" T="1781631781964" />
  <Point X="354" Y="580" T="1781631781965" />
  <Point X="351" Y="578" T="1781631781970" />
  <Point X="351" Y="578" T="1781631781971" />
  <Point X="350" Y="578" T="1781631781972" />
  <Point X="350" Y="578" T="1781631781973" />
  <Point X="349" Y="577" T="1781631781974" />
  <Point X="349" Y="577" T="1781631781975" />
  <Point X="348" Y="577" T="1781631781976" />
  <Point X="348" Y="576" T="1781631781977" />
  <Point X="347" Y="576" T="1781631781978" />
  <Point X="347" Y="575" T="1781631781979" />
  <Point X="347" Y="575" T="1781631781980" />
  <Point X="346" Y="575" T="1781631781981" />
  <Point X="346" Y="574" T="1781631781982" />
  <Point X="344" Y="572" T="1781631781987" />
  <Point X="343" Y="572" T="1781631781988" />
  <Point X="343" Y="571" T="1781631781989" />
  <Point X="343" Y="571" T="1781631781990" />
  <Point X="342" Y="571" T="1781631781992" />
  <Point X="342" Y="570" T="1781631781992" />
  <Point X="341" Y="569" T="1781631781993" />
  <Point X="341" Y="569" T="1781631781994" />
  <Point X="341" Y="568" T="1781631781995" />
  <Point X="340" Y="567" T="1781631781996" />
  <Point X="340" Y="567" T="1781631781997" />
  <Point X="340" Y="566" T="1781631781998" />
  <Point X="339" Y="566" T="1781631781999" />
  <Point X="338" Y="563" T="1781631782004" />
  <Point X="338" Y="562" T="1781631782004" />
  <Point X="338" Y="561" T="1781631782005" />
  <Point X="337" Y="560" T="1781631782006" />
  <Point X="337" Y="560" T="1781631782007" />
  <Point X="336" Y="559" T="1781631782009" />
  <Point X="336" Y="558" T="1781631782009" />
  <Point X="336" Y="556" T="1781631782010" />
  <Point X="336" Y="555" T="1781631782011" />
  <Point X="335" Y="554" T="1781631782012" />
  <Point X="335" Y="554" T="1781631782013" />
  <Point X="335" Y="553" T="1781631782014" />
  <Point X="335" Y="551" T="1781631782015" />
  <Point X="334" Y="551" T="1781631782016" />
  <Point X="332" Y="542" T="1781631782021" />
  <Point X="332" Y="541" T="1781631782022" />
  <Point X="332" Y="539" T="1781631782023" />
  <Point X="331" Y="535" T="1781631782024" />
  <Point X="330" Y="533" T="1781631782025" />
  <Point X="330" Y="532" T="1781631782026" />
  <Point X="330" Y="529" T="1781631782027" />
  <Point X="329" Y="528" T="1781631782028" />
  <Point X="329" Y="526" T="1781631782029" />
  <Point X="329" Y="525" T="1781631782030" />
  <Point X="329" Y="524" T="1781631782031" />
  <Point X="328" Y="523" T="1781631782032" />
  <Point X="328" Y="521" T="1781631782033" />
  <Point X="326" Y="512" T="1781631782038" />
  <Point X="326" Y="510" T="1781631782038" />
  <Point X="326" Y="509" T="1781631782039" />
  <Point X="326" Y="507" T="1781631782040" />
  <Point X="325" Y="505" T="1781631782043" />
  <Point X="325" Y="503" T="1781631782043" />
  <Point X="325" Y="502" T="1781631782044" />
  <Point X="324" Y="500" T="1781631782045" />
  <Point X="324" Y="494" T="1781631782047" />
  <Point X="323" Y="489" T="1781631782048" />
  <Point X="322" Y="487" T="1781631782049" />
  <Point X="321" Y="478" T="1781631782055" />
  <Point X="321" Y="478" T="1781631782055" />
  <Point X="321" Y="477" T="1781631782056" />
  <Point X="321" Y="475" T="1781631782057" />
  <Point X="321" Y="474" T="1781631782059" />
  <Point X="321" Y="473" T="1781631782059" />
  <Point X="321" Y="473" T="1781631782060" />
  <Point X="320" Y="471" T="1781631782061" />
  <Point X="320" Y="470" T="1781631782062" />
  <Point X="320" Y="469" T="1781631782063" />
  <Point X="320" Y="468" T="1781631782064" />
  <Point X="320" Y="468" T="1781631782065" />
  <Point X="320" Y="466" T="1781631782066" />
  <Point X="320" Y="466" T="1781631782072" />
</Gesture>